{
  "socialMedia": {
    "id": "social",
    "social": [
      {
        "label": "Social-Name",
        "platform": "linkedin",
        "url": "https://www.linkedin.com/in/name",
        "className": "bxl-linkedin-square"
      },
      {
        "label": "Social-Name",
        "platform": "github",
        "url": "https://github.com/name",
        "className": "bxl-github"
      },
      {
        "label": "Maaato",
        "platform": "twiiter",
        "url": "https://twitter.com/name",
        "className": "bxl-twitter"
      }
    ]
  }
}
